gem_controllers/__init__.py
gem_controllers/cascaded_controller.py
gem_controllers/current_controller.py
gem_controllers/gem_adapter.py
gem_controllers/gem_controller.py
gem_controllers/mpc_current_controller.py
gem_controllers/parameter_reader.py
gem_controllers/pi_current_controller.py
gem_controllers/pi_speed_controller.py
gem_controllers/reference_plotter.py
gem_controllers/torque_controller.py
gem_controllers/utils.py
gem_controllers/block_diagrams/__init__.py
gem_controllers/block_diagrams/block_diagram.py
gem_controllers/block_diagrams/stage_blocks/__init__.py
gem_controllers/block_diagrams/stage_blocks/eesm_cc.py
gem_controllers/block_diagrams/stage_blocks/eesm_ops.py
gem_controllers/block_diagrams/stage_blocks/eesm_output.py
gem_controllers/block_diagrams/stage_blocks/ext_ex_dc_cc.py
gem_controllers/block_diagrams/stage_blocks/ext_ex_dc_ops.py
gem_controllers/block_diagrams/stage_blocks/ext_ex_dc_output.py
gem_controllers/block_diagrams/stage_blocks/perm_ex_dc_cc.py
gem_controllers/block_diagrams/stage_blocks/perm_ex_dc_ops.py
gem_controllers/block_diagrams/stage_blocks/perm_ex_dc_output.py
gem_controllers/block_diagrams/stage_blocks/pi_speed_controller.py
gem_controllers/block_diagrams/stage_blocks/pmsm_cc.py
gem_controllers/block_diagrams/stage_blocks/pmsm_ops.py
gem_controllers/block_diagrams/stage_blocks/pmsm_output.py
gem_controllers/block_diagrams/stage_blocks/pmsm_sc.py
gem_controllers/block_diagrams/stage_blocks/scim_cc.py
gem_controllers/block_diagrams/stage_blocks/scim_ops.py
gem_controllers/block_diagrams/stage_blocks/scim_output.py
gem_controllers/block_diagrams/stage_blocks/scim_sc.py
gem_controllers/block_diagrams/stage_blocks/series_dc_cc.py
gem_controllers/block_diagrams/stage_blocks/series_dc_ops.py
gem_controllers/block_diagrams/stage_blocks/series_dc_output.py
gem_controllers/block_diagrams/stage_blocks/shunt_dc_cc.py
gem_controllers/block_diagrams/stage_blocks/shunt_dc_ops.py
gym_electric_motor-3.0.3.dist-info/METADATA
gym_electric_motor-3.0.3.dist-info/WHEEL
gym_electric_motor-3.0.3.dist-info/licenses/LICENSE
gym_electric_motor-3.0.3.dist-info/RECORD
