Metadata-Version: 2.4
Name: gym_electric_motor
Version: 3.0.3
Summary: A Farama Gymnasium environment for electric motor control.
Project-URL: Homepage, https://github.com/upb-lea/gym-electric-motor
Project-URL: Issues, https://github.com/upb-lea/gym-electric-motor/issues
Author: Arne Traue, Gerrit Book, Praneeth Balakrishna, Pascal Peters, Pramod Manjunatha, Darius Jakobeit, Felix Book, Max Schenke, Wilhelm Kirchgässner, Oliver Wallscheid, Barnabas Haucke-Korber, Stefan Arndt, Marius Köhler, Ranil Thomas, Manjeet Jha, Valliammai Annamalai, Mounica Vadivelu
License-File: LICENSE
Classifier: License :: OSI Approved :: MIT License
Classifier: Operating System :: OS Independent
Classifier: Programming Language :: Python :: 3
Requires-Python: >=3.9
Requires-Dist: gymnasium>=0.29.1
Requires-Dist: matplotlib>=3.1.2
Requires-Dist: numpy>=1.16.4
Requires-Dist: pathspec>=0.12.0
Requires-Dist: pytest-cov
Requires-Dist: pytest>=5.2.2
Requires-Dist: scipy>=1.4.1
